mcp_everythingcloudplatform/__init__.py
mcp_everythingcloudplatform/config.py
mcp_everythingcloudplatform/main.py
mcp_everythingcloudplatform/server.py
mcp_everythingcloudplatform/services/__init__.py
mcp_everythingcloudplatform/services/search_service.py
mcp_everythingcloudplatform/services/serpapi_client.py
mcp_everythingcloudplatform/utils/__init__.py
mcp_everythingcloudplatform/utils/logging.py
mcp_ecp-0.1.9.dist-info/METADATA
mcp_ecp-0.1.9.dist-info/WHEEL
mcp_ecp-0.1.9.dist-info/entry_points.txt
mcp_ecp-0.1.9.dist-info/top_level.txt
mcp_ecp-0.1.9.dist-info/RECORD
